ani_sched/__init__.py
ani_sched/_ani_sched.py
ani_sched/_base.py
ani_sched/config.py
ani_sched-0.1.3.dist-info/LICENSE
ani_sched-0.1.3.dist-info/METADATA
ani_sched-0.1.3.dist-info/WHEEL
ani_sched-0.1.3.dist-info/top_level.txt
ani_sched-0.1.3.dist-info/RECORD
